digital_cortex/Statement-Semantic-Sort-v2.py
digital_cortex/__init__.py
digital_cortex/client.py
digital_cortex/config.py
digital_cortex/datasets.py
digital_cortex/function_creator.py
digital_cortex/function_runner.py
digital_cortex/functions.py
digital_cortex/models.py
digital_cortex/pipelines.py
digital_cortex/schema/__init__.py
digital_cortex/schema/datasets.py
digital_cortex/schema/functions.py
digital_cortex/schema/models.py
digital_cortex/schema/pipelines.py
digital_cortex/schema/scoring.py
digital_cortex/schema/tags.py
digital_cortex/scoring.py
digital_cortex/tags.py
digital_cortex-0.0.40.dist-info/LICENSE.md
digital_cortex-0.0.40.dist-info/METADATA
digital_cortex-0.0.40.dist-info/WHEEL
digital_cortex-0.0.40.dist-info/RECORD
