Metadata-Version: 2.1
Name: digital-cortex
Version: 0.0.40
Summary: Python Client for Digital Cortex
Author: Charlie Wardell
Author-email: charlie@digital-cortex.io
Requires-Python: >=3.10,<4.0
Classifier: License :: OSI Approved :: MIT License
Classifier: Operating System :: OS Independent
Classifier: Programming Language :: Python :: 3
Classifier: Programming Language :: Python :: 3.10
Classifier: Programming Language :: Python :: 3.11
Requires-Dist: pydantic (>=2.1.1,<3.0.0)
Requires-Dist: requests (>=2.31.0,<3.0.0)
